osn_system_utils/__init__.py
osn_system_utils/exceptions.py
osn_system_utils/utils.py
osn_system_utils/api/__init__.py
osn_system_utils/api/_functions.py
osn_system_utils/api/_utils.py
osn_system_utils/api/network.py
osn_system_utils/api/process.py
osn_system_utils/linux/__init__.py
osn_system_utils/linux/kill.py
osn_system_utils/linux/shutdown.py
osn_system_utils/linux/ss.py
osn_system_utils/windows/__init__.py
osn_system_utils/windows/netstat.py
osn_system_utils/windows/shutdown.py
osn_system_utils/windows/taskkill.py
osn_system_utils-0.0.4.dist-info/METADATA
osn_system_utils-0.0.4.dist-info/WHEEL
osn_system_utils-0.0.4.dist-info/top_level.txt
osn_system_utils-0.0.4.dist-info/RECORD
