Metadata-Version: 2.4
Name: osn-system-utils
Version: 0.0.4
Summary: This library provides a set of Python abstractions for common system administration tasks on Linux and Windows, as well as utilities for network port management.
Author: oddshellnick
Author-email: oddshellnick.programming@gmail.com
Requires-Dist: psutil<8.0.0,>=7.2.0
Dynamic: author
Dynamic: author-email
Dynamic: description
Dynamic: description-content-type
Dynamic: requires-dist
Dynamic: summary
